enap_designsystem/__init__.py
enap_designsystem/apps.py
enap_designsystem/context_processors.py
enap_designsystem/models.py
enap_designsystem/settings.py
enap_designsystem/signals.py
enap_designsystem/urls.py
enap_designsystem/views.py
enap_designsystem/wagtail_hooks.py
enap_designsystem/blocks/__init__.py
enap_designsystem/blocks/base_blocks.py
enap_designsystem/blocks/chatbot_blocks.py
enap_designsystem/blocks/content_blocks.py
enap_designsystem/blocks/form.py
enap_designsystem/blocks/html_blocks.py
enap_designsystem/blocks/layout_blocks.py
enap_designsystem/blocks/liia.py
enap_designsystem/blocks/security.py
enap_designsystem/blocks/semana_blocks.py
enap_designsystem/blocks/semana_inovacao.py
enap_designsystem/middleware/__init__.py
enap_designsystem/middleware/aluno_sso.py
enap_designsystem/middleware/filtro_inputs.py
enap_designsystem/middleware/wagtail_userbar_safe.py
enap_designsystem/migrations/0001_initial.py
enap_designsystem/migrations/0002_alter_enapformacao_accordion_cursos.py
enap_designsystem/migrations/0003_mbaespecializacao.py
enap_designsystem/migrations/0004_mbaespecializacao_content.py
enap_designsystem/migrations/0005_mbaespecializacao_why_choose.py
enap_designsystem/migrations/0006_mbaespecializacao_navbar_templateespecializacao.py
enap_designsystem/migrations/0007_templateespecializacao_feature_estrutura.py
enap_designsystem/migrations/0008_templateespecializacao_feature_processo_seletivo.py
enap_designsystem/migrations/0009_templateespecializacao_team_carousel.py
enap_designsystem/migrations/0010_mbaespecializacao_footer_and_more.py
enap_designsystem/migrations/0011_mbaespecializacao_testimonials_carousel.py
enap_designsystem/migrations/0012_mbaespecializacao_preview_courses.py
enap_designsystem/migrations/0013_alter_mbaespecializacao_preview_courses.py
enap_designsystem/migrations/0014_mbaespecializacao_teste_noticia.py
enap_designsystem/migrations/0015_alter_mbaespecializacao_course_intro_topics_and_more.py
wagtail_enap_designsystem-1.2.1.246.dist-info/licenses/LICENSE
wagtail_enap_designsystem-1.2.1.246.dist-info/METADATA
wagtail_enap_designsystem-1.2.1.246.dist-info/WHEEL
wagtail_enap_designsystem-1.2.1.246.dist-info/top_level.txt
wagtail_enap_designsystem-1.2.1.246.dist-info/RECORD
