Metadata-Version: 2.4
Name: wagtail-enap-designsystem
Version: 1.2.1.246
Summary: Módulo de componentes utilizado nos portais ENAP, desenvolvido com Wagtail + CodeRedCMS
Author: Renan Campos
Author-email: renan.oliveira@enap.gov.br
License-File: LICENSE
Requires-Dist: django>=3.2
Requires-Dist: wagtail==6.4
Requires-Dist: coderedcms==4.1
Dynamic: author
Dynamic: author-email
Dynamic: description
Dynamic: description-content-type
Dynamic: license-file
Dynamic: requires-dist
Dynamic: summary
